{
  "TimeoutMs": 1500,
  "PingTimeoutMs": 800,
  "RequirePingForOnline": true,
  "TestPingWhenTcpFails": true,
  "OnlyShowOffline": false,
  "ReportPath": "output/last-report.json",
  "SummaryPath": "output/last-summary.json",
  "StatePath": "output/monitor-state.json",
  "LogDirectory": "output/logs",
  "Alert": {
    "Enabled": true,
    "FailureThreshold": 3,
    "RecoveryThreshold": 2,
    "ReminderMinutes": 60,
    "From": "2504601121@qq.com",
    "To": [
      "195836303@qq.com",
      "3198127828@qq.com"
    ],
    "SmtpHost": "smtp.qq.com",
    "SmtpPort": 587,
    "UseSsl": true,
    "UserName": "2504601121@qq.com",
    "Password": "tibskdiwwcvoecge",
    "SubjectPrefix": "[PC-Monitor]"
  }
}
